mds_account_invoice_deliverydate-4.6.0.dist-info/DESCRIPTION.rst
mds_account_invoice_deliverydate-4.6.0.dist-info/METADATA
mds_account_invoice_deliverydate-4.6.0.dist-info/RECORD
mds_account_invoice_deliverydate-4.6.0.dist-info/WHEEL
mds_account_invoice_deliverydate-4.6.0.dist-info/entry_points.txt
mds_account_invoice_deliverydate-4.6.0.dist-info/metadata.json
mds_account_invoice_deliverydate-4.6.0.dist-info/top_level.txt
trytond/modules/account_invoice_deliverydate/README.rst
trytond/modules/account_invoice_deliverydate/__init__.py
trytond/modules/account_invoice_deliverydate/invoice.py
trytond/modules/account_invoice_deliverydate/invoice.xml
trytond/modules/account_invoice_deliverydate/tryton.cfg
trytond/modules/account_invoice_deliverydate/locale/de.po
trytond/modules/account_invoice_deliverydate/view/invoice_form.xml
