Metadata-Version: 2.0
Name: mds-account-invoice-deliverydate
Version: 4.6.0
Summary: Tryton module to add delivery-date to invoices
Home-page: https://www.m-ds.de/
Author: m-ds GmbH
Author-email: service@m-ds.de
License: GPL-3
Keywords: tryton invoice delivery date
Platform: UNKNOWN
Classifier: Development Status :: 5 - Production/Stable
Classifier: Environment :: Plugins
Classifier: Framework :: Tryton
Classifier: Intended Audience :: Developers
Classifier: Intended Audience :: Customer Service
Classifier: Intended Audience :: Information Technology
Classifier: Intended Audience :: Financial and Insurance Industry
Classifier: Topic :: Office/Business
Classifier: Topic :: Office/Business :: Financial :: Accounting
Classifier: Natural Language :: German
Classifier: Natural Language :: English
Classifier: Operating System :: OS Independent
Classifier: License :: OSI Approved :: GNU General Public License (GPL)
Classifier: Programming Language :: Python :: 2.7
Classifier: Programming Language :: Python :: 3.4
Classifier: Programming Language :: Python :: 3.5
Classifier: Programming Language :: Python :: 3.6
Requires-Dist: trytond-account-invoice (<4.7,>=4.6)
Requires-Dist: trytond (<4.7,>=4.6)
